klib/__init__.py
klib/_version.py
klib/clean.py
klib/describe.py
klib/utils.py
klib/scripts/__init__.py
klib/scripts/performance.py
klib-1.4.0.dist-info/METADATA
klib-1.4.0.dist-info/WHEEL
klib-1.4.0.dist-info/licenses/LICENSE
klib-1.4.0.dist-info/RECORD
