Metadata-Version: 2.4
Name: klib
Version: 1.4.0
Summary: Common data preprocessing and visualisation functions.
Author-email: Andreas Kanz <andreas@akanz.de>
License-Expression: MIT
License-File: LICENSE
Classifier: License :: OSI Approved :: MIT License
Classifier: Operating System :: OS Independent
Classifier: Programming Language :: Python :: 3
Requires-Python: >=3.10
Requires-Dist: jinja2>=3.1.0
Requires-Dist: matplotlib>=3.9.0
Requires-Dist: numpy>=2.0.0
Requires-Dist: pandas<4.0,>=1.4
Requires-Dist: plotly>=5.24.0
Requires-Dist: scipy>=1.14.0
Requires-Dist: screeninfo>=0.8.1
Requires-Dist: seaborn>=0.13.0
